__init__.py
redis.py
simhash.py
mih_simhash-0.0.8.dist-info/METADATA
mih_simhash-0.0.8.dist-info/WHEEL
mih_simhash-0.0.8.dist-info/namespace_packages.txt
mih_simhash-0.0.8.dist-info/top_level.txt
mih_simhash-0.0.8.dist-info/zip-safe
mih_simhash-0.0.8.dist-info/RECORD
